gaelalgebra/__init__.py
gaelalgebra/example.py
gaelalgebra-0.0.2.dist-info/METADATA
gaelalgebra-0.0.2.dist-info/WHEEL
gaelalgebra-0.0.2.dist-info/RECORD
